resosuma/__init__.py
resosuma/exceptions.py
resosuma/version.py
resosuma/visualizer.py
resosuma/graph/__init__.py
resosuma/graph/activitygraph.py
resosuma/graph/edge.py
resosuma/graph/node.py
resosuma-0.2.0.dist-info/METADATA
resosuma-0.2.0.dist-info/RECORD
resosuma-0.2.0.dist-info/WHEEL
resosuma-0.2.0.dist-info/top_level.txt
