Metadata-Version: 2.1
Name: resosuma
Version: 0.2.0
Summary: A package providing mappings of the research software sustainability space.
Home-page: https://github.com/research-software/resosuma
Author: Stephan Druskat
Author-email: mail@sdruskat.net
License: Apache-2.0
Platform: UNKNOWN
Classifier: Development Status :: 4 - Beta
Classifier: Intended Audience :: Science/Research
Classifier: Programming Language :: Python :: 3.6
Requires-Dist: graphviz (==0.8.3)
